hussain/__init__.py
hussain/hussain.py
hussain/hussain1.py
hussain-1.0.dist-info/METADATA
hussain-1.0.dist-info/WHEEL
hussain-1.0.dist-info/top_level.txt
hussain-1.0.dist-info/RECORD
